StructResult/__init__.py
StructResult/formatter.py
StructResult/py.typed
StructResult/result.py
structresult-0.9.6.dist-info/METADATA
structresult-0.9.6.dist-info/WHEEL
structresult-0.9.6.dist-info/top_level.txt
structresult-0.9.6.dist-info/RECORD
