Metadata-Version: 2.4
Name: StructResult
Version: 0.9.6
Summary: structural result with ExceptionGroup
Author-email: Serj Kotilevski <youserj@outlook.com>
Project-URL: Source, https://github.com/youserj/Result_prj
Keywords: result,Exception,ExceptionGroup,AggregateExceptions
Classifier: Programming Language :: Python :: 3
Classifier: License :: OSI Approved :: MIT License
Classifier: Operating System :: OS Independent
Requires-Python: >=3.12
Provides-Extra: dev
Requires-Dist: mypy>=1.18.0; extra == "dev"
Requires-Dist: ruff>=0.11; extra == "dev"
Requires-Dist: types-requests; extra == "dev"
